json_xlsx/__init__.py
json_xlsx/config.py
json_xlsx/converter.py
json_xlsx/examples.py
json_xlsx/formatters.py
json_xlsx-0.1.0.dist-info/METADATA
json_xlsx-0.1.0.dist-info/WHEEL
json_xlsx-0.1.0.dist-info/licenses/LICENSE
json_xlsx-0.1.0.dist-info/RECORD
