Metadata-Version: 2.4
Name: json_xlsx
Version: 0.1.0
Summary: Convert nested JSON data to formatted Excel files
Project-URL: Homepage, https://github.com/quantatirsk/json_xlsx
Project-URL: Repository, https://github.com/quantatirsk/json_xlsx.git
Project-URL: Documentation, https://github.com/quantatirsk/json_xlsx#readme
Project-URL: Bug Tracker, https://github.com/quantatirsk/json_xlsx/issues
Author-email: Quant <pengzhia@gmail.com>
Maintainer-email: Quant <pengzhia@gmail.com>
License-Expression: MIT
License-File: LICENSE
Keywords: converter,data-processing,excel,json,openpyxl,pandas,xlsx
Classifier: Development Status :: 4 - Beta
Classifier: Intended Audience :: Developers
Classifier: License :: OSI Approved :: MIT License
Classifier: Operating System :: OS Independent
Classifier: Programming Language :: Python :: 3
Classifier: Programming Language :: Python :: 3.8
Classifier: Programming Language :: Python :: 3.9
Classifier: Programming Language :: Python :: 3.10
Classifier: Programming Language :: Python :: 3.11
Classifier: Programming Language :: Python :: 3.12
Classifier: Topic :: Office/Business :: Office Suites
Classifier: Topic :: Software Development :: Libraries :: Python Modules
Classifier: Topic :: Utilities
Requires-Python: >=3.8
Requires-Dist: openpyxl>=3.0.0
Requires-Dist: pandas>=2.0.0
Provides-Extra: dev
Requires-Dist: black; extra == 'dev'
Requires-Dist: flake8; extra == 'dev'
Requires-Dist: mypy; extra == 'dev'
Requires-Dist: pytest-cov; extra == 'dev'
Requires-Dist: pytest>=6.0; extra == 'dev'
Provides-Extra: test
Requires-Dist: pytest-cov; extra == 'test'
Requires-Dist: pytest>=6.0; extra == 'test'
